toodle/__init__.py
toodle/__main__.py
toodle/cli/__init__.py
toodle/cli/build.py
toodle/cli/validate.py
toodle/core/__init__.py
toodle/core/questions/__init__.py
toodle/core/questions/category.py
toodle/core/questions/coderunner.py
toodle/core/questions/multichoice.py
toodle/core/questions/question.py
toodle/core/questions/quiz.py
toodle/core/questions/shortanswer.py
toodle/core/serialization/__init__.py
toodle/core/serialization/serializable.py
toodle/core/serialization/serializer.py
toodle/core/serialization/schema_validation/__init__.py
toodle/core/serialization/schema_validation/validation.py
toodle/core/serialization/schema_validation/schemata/category.schema.json
toodle/core/serialization/schema_validation/schemata/coderunner.schema.json
toodle/core/serialization/schema_validation/schemata/multichoice.schema.json
toodle/core/serialization/schema_validation/schemata/question.schema.json
toodle/core/serialization/schema_validation/schemata/quiz.schema.json
toodle/core/serialization/schema_validation/schemata/shortanswer.schema.json
toodle/core/serialization/schema_validation/schemata/components/file.schema.json
toodle/core/serialization/schema_validation/schemata/components/markup.schema.json
toodle/core/serialization/schema_validation/schemata/components/unresolvedMarkup.schema.json
toodle/core/serialization/xml/serializer.py
toodle/core/serialization/xml/templates/category.xml
toodle/core/serialization/xml/templates/coderunner.xml
toodle/core/serialization/xml/templates/img.xml
toodle/core/serialization/xml/templates/multichoice.xml
toodle/core/serialization/xml/templates/quiz.xml
toodle/core/serialization/xml/templates/shortanswer.xml
toodle/utils/files.py
toodle/utils/images.py
toodle/utils/logs.py
toodle/utils/markup.py
toodle-1.0.0a9.dist-info/LICENSE
toodle-1.0.0a9.dist-info/METADATA
toodle-1.0.0a9.dist-info/WHEEL
toodle-1.0.0a9.dist-info/entry_points.txt
toodle-1.0.0a9.dist-info/top_level.txt
toodle-1.0.0a9.dist-info/RECORD
