Metadata-Version: 2.1
Name: toodle
Version: 1.0.0a9
Summary: A small transpiler that converts human-readable text and TOML file formats
License: MIT License
Keywords: Moodle
Classifier: Development Status :: 1 - Planning
Classifier: Topic :: Utilities
Classifier: Intended Audience :: Education
Classifier: Programming Language :: Python :: 3
Classifier: License :: OSI Approved :: MIT License
Requires-Python: >=3.11
License-File: LICENSE
Requires-Dist: Jinja2 (~=3.1.2)
Requires-Dist: jsonschema (~=4.17.3)
Requires-Dist: beautifulsoup4 (~=4.11.1)
Requires-Dist: markdown-it-py[linkify] (~=2.1.0)
Requires-Dist: typer[all] (~=0.7.0)
